serviceping/__init__.py
serviceping/__main__.py
serviceping/cli.py
serviceping/commandline.py
serviceping/network.py
serviceping/serviceping.py
serviceping-21.6.718832.dist-info/LICENSE.txt
serviceping-21.6.718832.dist-info/METADATA
serviceping-21.6.718832.dist-info/WHEEL
serviceping-21.6.718832.dist-info/entry_points.txt
serviceping-21.6.718832.dist-info/top_level.txt
serviceping-21.6.718832.dist-info/RECORD
