Metadata-Version: 2.1
Name: serviceping
Version: 21.6.718832
Summary: A command line utility that provides a ping like interface for checking tcp/ssl ports and services
Home-page: https://github.com/yahoo/serviceping
Author: Dwight Hubbard
Author-email: dhubbard@ouroath.com
License: Apache
Project-URL: CI Pipeline, https://cd.screwdriver.cd/pipelines/2881
Project-URL: Change History, https://yahoo.github.io/serviceping/changelog/
Project-URL: Documentation, https://yahoo.github.io/serviceping/
Project-URL: Source, https://github.com/yahoo/serviceping
Keywords: ping,network-analysis,troubleshooting,networking
Platform: UNKNOWN
Classifier: License :: OSI Approved :: Apache Software License
Classifier: Development Status :: 4 - Beta
Classifier: Environment :: Console
Classifier: Intended Audience :: Developers
Classifier: Operating System :: MacOS :: MacOS X
Classifier: Operating System :: POSIX :: BSD :: FreeBSD
Classifier: Operating System :: POSIX :: Linux
Classifier: Operating System :: POSIX :: SunOS/Solaris
Classifier: Operating System :: POSIX
Classifier: Programming Language :: Python :: 3.6
Classifier: Programming Language :: Python :: 3.7
Classifier: Programming Language :: Python :: 3.8
Classifier: Programming Language :: Python :: Implementation :: CPython
Classifier: Topic :: System :: Systems Administration
Classifier: Topic :: Utilities
Requires-Python: >=3.6
License-File: LICENSE.txt
Provides-Extra: doc_build
Requires-Dist: markdown-include ; extra == 'doc_build'
Requires-Dist: mkdocs-material ; extra == 'doc_build'
Requires-Dist: pygments ; extra == 'doc_build'
Requires-Dist: pymdown-extensions ; extra == 'doc_build'
Requires-Dist: recommonmark ; extra == 'doc_build'
